crypto_utils/__init__.py
crypto_utils/encrypt.py
crypto_utils/hash.py
crypto_utils/kdf.py
crypto_utils/sign.py
security_crypto_primitives-1.1.1.dist-info/METADATA
security_crypto_primitives-1.1.1.dist-info/WHEEL
security_crypto_primitives-1.1.1.dist-info/top_level.txt
security_crypto_primitives-1.1.1.dist-info/RECORD
