Metadata-Version: 2.4
Name: security-crypto-primitives
Version: 1.1.1
Summary: Обёртки и утилиты для шифрования, подписей и хеширования
Author: Ruslan
Requires-Python: >=3.7
Requires-Dist: cryptography>=41.0.0
